[
{ "marker_ID": 13, "Detection_Rate": 100.00 },
{ "marker_ID": 17, "Detection_Rate": 100.00 },
{ "marker_ID": 49, "Detection_Rate": 100.00 },
{ "marker_ID": 62, "Detection_Rate": 100.00 },
{ "marker_ID": 41, "Detection_Rate": 100.00 },
{ "marker_ID": 107, "Detection_Rate": 100.00 },
{ "marker_ID": 110, "Detection_Rate": 100.00 },
{ "marker_ID": 126, "Detection_Rate": 100.00 },
{ "marker_ID": 112, "Detection_Rate": 100.00 },
{ "marker_ID": 140, "Detection_Rate": 100.00 },
{ "marker_ID": 118, "Detection_Rate": 100.00 },
{ "marker_ID": 145, "Detection_Rate": 100.00 },
{ "marker_ID": 147, "Detection_Rate": 100.00 },
{ "marker_ID": 157, "Detection_Rate": 100.00 },
{ "marker_ID": 164, "Detection_Rate": 100.00 },
{ "marker_ID": 163, "Detection_Rate": 100.00 },
{ "marker_ID": 196, "Detection_Rate": 100.00 },
{ "marker_ID": 366, "Detection_Rate": 100.00 },
{ "marker_ID": 425, "Detection_Rate": 100.00 },
{ "marker_ID": 336, "Detection_Rate": 100.00 },
{ "marker_ID": 422, "Detection_Rate": 100.00 },
{ "marker_ID": 434, "Detection_Rate": 100.00 },
{ "marker_ID": 327, "Detection_Rate": 100.00 },
{ "marker_ID": 404, "Detection_Rate": 100.00 },
{ "marker_ID": 430, "Detection_Rate": 100.00 },
{ "marker_ID": 486, "Detection_Rate": 100.00 },
{ "marker_ID": 467, "Detection_Rate": 100.00 },
{ "marker_ID": 371, "Detection_Rate": 100.00 },
{ "marker_ID": 416, "Detection_Rate": 100.00 },
{ "marker_ID": 460, "Detection_Rate": 100.00 },
{ "marker_ID": 464, "Detection_Rate": 100.00 },
{ "marker_ID": 340, "Detection_Rate": 100.00 },
{ "marker_ID": 439, "Detection_Rate": 100.00 },
{ "marker_ID": 479, "Detection_Rate": 100.00 },
{ "marker_ID": 346, "Detection_Rate": 100.00 },
{ "marker_ID": 468, "Detection_Rate": 100.00 },
{ "marker_ID": 640, "Detection_Rate": 100.00 },
{ "marker_ID": 698, "Detection_Rate": 100.00 },
{ "marker_ID": 691, "Detection_Rate": 100.00 },
{ "marker_ID": 575, "Detection_Rate": 100.00 },
{ "marker_ID": 710, "Detection_Rate": 100.00 },
{ "marker_ID": 660, "Detection_Rate": 100.00 },
{ "marker_ID": 703, "Detection_Rate": 100.00 },
{ "marker_ID": 658, "Detection_Rate": 100.00 },
{ "marker_ID": 705, "Detection_Rate": 100.00 },
{ "marker_ID": 562, "Detection_Rate": 100.00 },
{ "marker_ID": 696, "Detection_Rate": 100.00 },
{ "marker_ID": 580, "Detection_Rate": 100.00 },
{ "marker_ID": 689, "Detection_Rate": 100.00 },
{ "marker_ID": 638, "Detection_Rate": 100.00 },
{ "marker_ID": 809, "Detection_Rate": 100.00 },
{ "marker_ID": 941, "Detection_Rate": 100.00 },
{ "marker_ID": 874, "Detection_Rate": 100.00 },
{ "marker_ID": 959, "Detection_Rate": 100.00 },
{ "marker_ID": 864, "Detection_Rate": 100.00 },
{ "marker_ID": 803, "Detection_Rate": 100.00 },
{ "marker_ID": 898, "Detection_Rate": 100.00 },
{ "marker_ID": 946, "Detection_Rate": 100.00 },
{ "marker_ID": 942, "Detection_Rate": 100.00 },
{ "marker_ID": 813, "Detection_Rate": 100.00 },
{ "marker_ID": 917, "Detection_Rate": 100.00 },
{ "marker_ID": 771, "Detection_Rate": 100.00 },
{ "marker_ID": 794, "Detection_Rate": 100.00 },
{ "marker_ID": 795, "Detection_Rate": 100.00 },
{ "marker_ID": 883, "Detection_Rate": 100.00 },
{ "marker_ID": 888, "Detection_Rate": 100.00 },
{ "marker_ID": 773, "Detection_Rate": 100.00 },
{ "marker_ID": 929, "Detection_Rate": 100.00 },
{ "marker_ID": 778, "Detection_Rate": 100.00 },
{ "marker_ID": 806, "Detection_Rate": 100.00 },
{ "marker_ID": 775, "Detection_Rate": 100.00 },
{ "marker_ID": 853, "Detection_Rate": 100.00 }
]